renard/__init__.py
renard/__main__.py
renard/cli.py
renard/eng.py
renard/renard.py
renard/version.py
renard-1.3.13.dist-info/LICENSE.txt
renard-1.3.13.dist-info/METADATA
renard-1.3.13.dist-info/WHEEL
renard-1.3.13.dist-info/entry_points.txt
renard-1.3.13.dist-info/top_level.txt
renard-1.3.13.dist-info/RECORD
