Metadata-Version: 2.1
Name: renard
Version: 1.3.13
Summary: Working with the Renard series of preferred numbers specified in ISO 3.
Home-page: https://github.com/rob-smallshire/renard
Author: Robert Smallshire
Author-email: rob@sixty-north.com
License: MIT License
Keywords: engineering preferred-numbers
Platform: UNKNOWN
Classifier: Development Status :: 5 - Production/Stable
Classifier: Intended Audience :: Developers
Classifier: Topic :: Scientific/Engineering
Classifier: Topic :: Software Development :: Libraries
Classifier: License :: OSI Approved :: MIT License
Classifier: Programming Language :: Python :: 3 :: Only
Classifier: Programming Language :: Python :: 3.4
Classifier: Programming Language :: Python :: 3.5
Classifier: Programming Language :: Python :: 3.6
License-File: LICENSE.txt
Requires-Dist: docopt-subcommands (>=4.0)
Provides-Extra: dev
Requires-Dist: check-manifest ; extra == 'dev'
Requires-Dist: wheel ; extra == 'dev'
Requires-Dist: bumpversion ; extra == 'dev'
Provides-Extra: doc
Requires-Dist: sphinx ; extra == 'doc'
Requires-Dist: cartouche ; extra == 'doc'
Provides-Extra: test
Requires-Dist: coverage ; extra == 'test'
Requires-Dist: hypothesis ; extra == 'test'
Requires-Dist: pytest ; extra == 'test'
